__init__.py
main.py
simulations.py
laby-0.0.0.dist-info/LICENSE
laby-0.0.0.dist-info/METADATA
laby-0.0.0.dist-info/WHEEL
laby-0.0.0.dist-info/entry_points.txt
laby-0.0.0.dist-info/top_level.txt
laby-0.0.0.dist-info/RECORD
