Metadata-Version: 2.1
Name: laby
Version: 0.0.0
Summary: A CLI tool for running simulations
Author-email: Your Name <your.email@example.com>
License: MIT
Project-URL: Homepage, https://github.com/Labyrinth-Technologies/laby-py
Classifier: Programming Language :: Python :: 3
Classifier: License :: OSI Approved :: MIT License
Classifier: Operating System :: OS Independent
License-File: LICENSE
Requires-Dist: click
